iget/__init__.py
iget/main.py
iget-0.5.0.dist-info/METADATA
iget-0.5.0.dist-info/WHEEL
iget-0.5.0.dist-info/entry_points.txt
iget-0.5.0.dist-info/top_level.txt
iget-0.5.0.dist-info/RECORD
