Metadata-Version: 2.1
Name: iget
Version: 0.5.0
Summary: A small CLI
Home-page: https://pypi.org/project/iget/
Author: nethead
Author-email: netheadonline@gmail.com
License: UNKNOWN
Platform: UNKNOWN
Classifier: Programming Language :: Python :: 3
Classifier: License :: OSI Approved :: MIT License
Classifier: Operating System :: OS Independent
Requires-Python: >=3.6
